query_optimizer/__init__.py
query_optimizer/ast.py
query_optimizer/compiler.py
query_optimizer/converters.py
query_optimizer/errors.py
query_optimizer/fields.py
query_optimizer/filter.py
query_optimizer/filter_info.py
query_optimizer/optimizer.py
query_optimizer/prefetch_hack.py
query_optimizer/py.typed
query_optimizer/selections.py
query_optimizer/settings.py
query_optimizer/types.py
query_optimizer/typing.py
query_optimizer/utils.py
query_optimizer/validators.py
graphene_django_query_optimizer-0.10.15.dist-info/LICENSE
graphene_django_query_optimizer-0.10.15.dist-info/METADATA
graphene_django_query_optimizer-0.10.15.dist-info/WHEEL
graphene_django_query_optimizer-0.10.15.dist-info/RECORD
