Metadata-Version: 2.3
Name: graphene-django-query-optimizer
Version: 0.10.15
Summary: Automatically optimize SQL queries in Graphene-Django schemas.
License: MIT
Keywords: django,graphene,sql,graphql,python,query,optimizer,optimization
Author: Matti Lamppu
Author-email: lamppu.matti.akseli@gmail.com
Requires-Python: >=3.11,<4
Classifier: Environment :: Web Environment
Classifier: Operating System :: OS Independent
Classifier: Intended Audience :: Developers
Classifier: Natural Language :: English
Classifier: Programming Language :: Python
Classifier: Programming Language :: Python :: 3
Classifier: Programming Language :: Python :: 3 :: Only
Classifier: Programming Language :: Python :: 3.11
Classifier: Programming Language :: Python :: 3.12
Classifier: Programming Language :: Python :: 3.13
Classifier: Framework :: Django :: 5.0
Classifier: Framework :: Django :: 5.1
Classifier: Framework :: Django :: 5.2
Requires-Dist: Django (>=5.0)
Requires-Dist: django-settings-holder (>=0.1.2)
Requires-Dist: graphene-django (>=3.0.0)
Project-URL: Bug Tracker, https://github.com/MrThearMan/graphene-django-query-optimizer/issues
Project-URL: Documentation, https://mrthearman.github.io/graphene-django-query-optimizer
Project-URL: Homepage, https://mrthearman.github.io/graphene-django-query-optimizer
Project-URL: Repository, https://github.com/MrThearMan/graphene-django-query-optimizer
